<theme>
	<formatVersion>4</formatVersion>

	<view name="system">
		<text name="info1" extra="true">
			<text>Mario is a media franchise, published and produced by Nintendo, starring the fictional Italian character Mario. It is primarily a video game franchise, with the franchise's other forms of media including several television series and a feature film.</text>
		</text>

		<text name="info1" extra="true" lang="PT">
			<text>Mario é uma franquia de mídia, publicada e produzida pela Nintendo, estrelando o personagem Mario. É uma franquia de videogame, com outras formas de mídia , incluindo várias séries de televisão e um longa-metragem.</text>
		</text>

				<text name="info1" extra="true" lang="EN">
			<text>Mario is a media franchise, published and produced by Nintendo, starring the fictional Italian character Mario. It is primarily a video game franchise, with the franchise's other forms of media including several television series and a feature film.</text>
		</text>

				<text name="info1" extra="true" lang="ES">
			<text>Mario es una franquicia de medios, publicada y producida por Nintendo, protagonizada por el personaje Mario. Es principalmente una franquicia de videojuegos, con otras formas de medios de la franquicia que incluyen varias series de televisión y una película.</text>
		</text>

				<text name="info1" extra="true" lang="FR">
			<text>Mario est une franchise média, publiée et produite par Nintendo, avec le personnage Mario. Il s'agit principalement d'une franchise de jeux vidéo, avec les autres formes de médias de la franchise, notamment plusieurs séries télévisées et un long métrage.</text>
		</text>

		<text name="info1" extra="true" lang="DE">
			<text>Mario ist ein von Nintendo veröffentlichtes und produziertes Medien-Franchise mit der fiktiven italienischen Figur Mario in der Hauptrolle. Es ist in erster Linie ein Videospiel-Franchise, wobei die anderen Medienformen des Franchise mehrere Fernsehserien und einen Spielfilm umfassen.</text>
		</text>

				<text name="info2" extra="true">
			<text>Super Mario</text>
		</text>

		<text name="info3" extra="true">
			<text>1981</text>
		</text>

		<text name="info4" extra="true">
			<text>Shigeru Miyamoto</text>
		</text>

		<text name="info5" extra="true">
			<text>DEVELOPER:</text>
		</text>

				<text name="info5" extra="true"  lang="PT">
			<text>DESENVOLVEDOR:</text>
		</text>
						<text name="info5" extra="true" lang="EN">
			<text>DEVELOPER:</text>
		</text>
						<text name="info5" extra="true" lang="ES">
			<text>DESARROLLADOR:</text>
		</text>
						<text name="info5" extra="true" lang="FR">
			<text>DÉVELOPPEUR:</text>
		</text>
		
				<text name="info5" extra="true" lang="DE">
			<text>ENTWICKLER:</text>
		</text>
		
	</view>
<customView name="TLTL-CUSTOM" inherits="gamecarousel" tinyScreen="false" displayName="${tltlcustom}">
<image name="md_thumbnail"><pos>0.54 0.5</pos><size>0.160 0.000</size><zIndex>36</zIndex></image>
</customView>
<customView name="TLTL-NO-VIDEO" inherits="gamecarousel" tinyScreen="false" displayName="TLTL-NO-VIDEO">
<image name="md_thumbnail"><pos>0.54 0.5</pos><size>0.160 0.000</size><zIndex>36</zIndex></image>
</customView>
<customView name="TLTL-NO-FANART" inherits="gamecarousel" tinyScreen="false" displayName="TLTL-NO-FANART">
<image name="md_thumbnail"><pos>0.54 0.5</pos><size>0.160 0.000</size><zIndex>36</zIndex></image>
</customView>
<customView name="TLTL-CUSTOM-NO-VID/ART" inherits="gamecarousel" tinyScreen="false" displayName="TLTL-NO-VIDEO/ART">
<image name="md_thumbnail"><pos>0.54 0.5</pos><size>0.160 0.000</size><zIndex>36</zIndex></image>
</customView>
<customView name="TLTL-COLOR" inherits="gamecarousel" tinyScreen="false" displayName="TLTL-COLOR">
<image name="md_thumbnail"><pos>0.54 0.5</pos><size>0.160 0.000</size><zIndex>36</zIndex></image>
</customView>

		
<customView name="TLTL-HCoinSpin">
<image name="md_thumbnail" extra="true"><pos>0.088 0.80</pos><size>0.10 0</size><zIndex>36</zIndex></image>
      <image name="art3" extra="true">
         <path>./../assets/coinops/default.png</path>
         <zIndex>7</zIndex>
      </image>
	
</customView>


	
<customView name="TLTL-CoinOps">
<image name="md_thumbnail" extra="true"><pos>0.088 0.89</pos><size>0.10 0</size><zIndex>36</zIndex></image>
      <image name="art3" extra="true">
         <path>./../assets/coinops/default.png</path>
         <zIndex>7</zIndex>
      </image>
	
</customView>

<view name="gamecarousel">
<image name="logo">
<path>./assets/logos/${system.theme}.png</path>
<path>./assets/logos/${system.theme}.svg</path>
<pos>0.122 0.035</pos>
<size>0.20 0</size>
<alignment>center</alignment>
<zIndex>150</zIndex>
<linearSmooth>true</linearSmooth>
</image>
<image name="console" aspect="true" extra="true"><path>./assets/consoles/${system.theme}.png</path><pos>0.325 0.875</pos><origin>0.5 0.5</origin><maxSize>0.20 .20</maxSize><zIndex>150</zIndex><storyboard><animation property="opacity" from="0" to="0" begin="0" duration="1" mode="linear"/><animation property="opacity" from="0" to="1" begin="0" duration="300" mode="linear"/></storyboard></image></view>

<customView name="TLTL-CoinOps" inherits="grid" tinyScreen="false" displayName="${hcoinopsdViewName}">
<image name="md_thumbnail" extra="true"><pos>0.0360 0.785</pos><size>0.090 0.000</size><origin>0 0</origin><zIndex>111</zIndex></image>
</customView>

</theme>
